KouziPy/LayerClass.py
KouziPy/ModelClass.py
KouziPy/__init__.py
KouziPy/neuroneClasse.py
KouziPy-0.1.0.dist-info/METADATA
KouziPy-0.1.0.dist-info/WHEEL
KouziPy-0.1.0.dist-info/top_level.txt
KouziPy-0.1.0.dist-info/RECORD
