Metadata-Version: 2.1
Name: KouziPy
Version: 0.1.0
Summary: A deep learning librairy
Home-page: UNKNOWN
License: UNKNOWN
Platform: UNKNOWN
